{
    "key": "group_589f34beb26e1",
    "title": "Settings: Leading Area",
    "fields": [
        {
            "key": "field_589f34beb4f59",
            "label": "Activation",
            "name": "leading_area_show",
            "type": "true_false",
            "instructions": "Show a additional area for specific or all sites. This area is displayed below the main menu and above the content.",
            "required": 0,
            "conditional_logic": 0,
            "wrapper": {
                "width": "100",
                "class": "",
                "id": ""
            },
            "message": "",
            "default_value": 0,
            "ui": 1,
            "ui_on_text": "Yes",
            "ui_off_text": "No"
        },
        {
            "key": "field_589f34beb4fc6",
            "label": "Section(s)",
            "name": "add_leading_area",
            "type": "repeater",
            "instructions": "",
            "required": 0,
            "conditional_logic": [
                [
                    {
                        "field": "field_589f34beb4f59",
                        "operator": "==",
                        "value": "1"
                    }
                ]
            ],
            "wrapper": {
                "width": "",
                "class": "",
                "id": ""
            },
            "collapsed": "",
            "min": 0,
            "max": 0,
            "layout": "row",
            "button_label": "Add new",
            "sub_fields": [
                {
                    "key": "field_594651f144229",
                    "label": "Visibility",
                    "name": "",
                    "type": "tab",
                    "instructions": "",
                    "required": 0,
                    "conditional_logic": 0,
                    "wrapper": {
                        "width": "",
                        "class": "",
                        "id": ""
                    },
                    "placement": "top",
                    "endpoint": 0
                },
                {
                    "key": "field_5a75cd7134c87",
                    "label": "Content",
                    "name": "area_content",
                    "type": "select",
                    "instructions": "",
                    "required": 0,
                    "conditional_logic": 0,
                    "wrapper": {
                        "width": "",
                        "class": "",
                        "id": ""
                    },
                    "choices": {
                        "carousel": "Post, Product, Category or Tag Carousel",
                        "promobox": "Promo Boxes",
                        "banner": "Random Ad Banner",
                        "content_grid": "Content Grid",
                        "html": "Custom HTML"
                    },
                    "default_value": [],
                    "allow_null": 0,
                    "multiple": 0,
                    "ui": 1,
                    "ajax": 1,
                    "return_format": "value",
                    "placeholder": ""
                },
                {
                    "key": "field_5a031c901f542",
                    "label": "Visibility Selection",
                    "name": "visibility_selection",
                    "type": "clone",
                    "instructions": "",
                    "required": 0,
                    "conditional_logic": 0,
                    "wrapper": {
                        "width": "",
                        "class": "",
                        "id": ""
                    },
                    "clone": [
                        "group_5a6e078169976"
                    ],
                    "display": "seamless",
                    "layout": "block",
                    "prefix_label": 0,
                    "prefix_name": 0
                },
                {
                    "key": "field_58b030f5914de",
                    "label": "Position",
                    "name": "leading_area_position",
                    "type": "select",
                    "instructions": "",
                    "required": 0,
                    "conditional_logic": 0,
                    "wrapper": {
                        "width": "50",
                        "class": "",
                        "id": ""
                    },
                    "choices": {
                        "above_header": "Above the Header",
                        "below_header": "Below the Header"
                    },
                    "default_value": [
                        "above_header"
                    ],
                    "allow_null": 0,
                    "multiple": 0,
                    "ui": 0,
                    "ajax": 0,
                    "return_format": "value",
                    "placeholder": ""
                },
                {
                    "key": "field_5a75cd4034c86",
                    "label": "Carousel",
                    "name": "",
                    "type": "tab",
                    "instructions": "",
                    "required": 0,
                    "conditional_logic": [
                        [
                            {
                                "field": "field_5a75cd7134c87",
                                "operator": "==",
                                "value": "carousel"
                            }
                        ]
                    ],
                    "wrapper": {
                        "width": "",
                        "class": "",
                        "id": ""
                    },
                    "placement": "top",
                    "endpoint": 0
                },
                {
                    "key": "field_5a75cd1834c85",
                    "label": "Carousel Selection",
                    "name": "carousel_selection",
                    "type": "clone",
                    "instructions": "",
                    "required": 0,
                    "conditional_logic": 0,
                    "wrapper": {
                        "width": "",
                        "class": "",
                        "id": ""
                    },
                    "clone": [
                        "group_5a75cb21e2ebe"
                    ],
                    "display": "seamless",
                    "layout": "block",
                    "prefix_label": 0,
                    "prefix_name": 0
                },
                {
                    "key": "field_5a75ce2334c8c",
                    "label": "Promo Boxes",
                    "name": "",
                    "type": "tab",
                    "instructions": "",
                    "required": 0,
                    "conditional_logic": [
                        [
                            {
                                "field": "field_5a75cd7134c87",
                                "operator": "==",
                                "value": "promobox"
                            }
                        ]
                    ],
                    "wrapper": {
                        "width": "",
                        "class": "",
                        "id": ""
                    },
                    "placement": "top",
                    "endpoint": 0
                },
                {
                    "key": "field_5a75ce3934c8d",
                    "label": "Promo Boxes Selection",
                    "name": "promo_boxes_selection",
                    "type": "clone",
                    "instructions": "",
                    "required": 0,
                    "conditional_logic": 0,
                    "wrapper": {
                        "width": "",
                        "class": "",
                        "id": ""
                    },
                    "clone": [
                        "group_5a75cc9f6177f"
                    ],
                    "display": "seamless",
                    "layout": "block",
                    "prefix_label": 0,
                    "prefix_name": 0
                },
                {
                    "key": "field_5a75cdf534c8a",
                    "label": "Random Ad Banner",
                    "name": "",
                    "type": "tab",
                    "instructions": "",
                    "required": 0,
                    "conditional_logic": [
                        [
                            {
                                "field": "field_5a75cd7134c87",
                                "operator": "==",
                                "value": "banner"
                            }
                        ]
                    ],
                    "wrapper": {
                        "width": "",
                        "class": "",
                        "id": ""
                    },
                    "placement": "top",
                    "endpoint": 0
                },
                {
                    "key": "field_5a75ce0334c8b",
                    "label": "Random Ad Banner Selection",
                    "name": "random_ad_banner_selection",
                    "type": "clone",
                    "instructions": "",
                    "required": 0,
                    "conditional_logic": 0,
                    "wrapper": {
                        "width": "",
                        "class": "",
                        "id": ""
                    },
                    "clone": [
                        "group_5a75ccda7e738"
                    ],
                    "display": "seamless",
                    "layout": "block",
                    "prefix_label": 0,
                    "prefix_name": 0
                },
                {
                    "key": "field_5a7aeac55b776",
                    "label": "Content Grid",
                    "name": "",
                    "type": "tab",
                    "instructions": "",
                    "required": 0,
                    "conditional_logic": [
                        [
                            {
                                "field": "field_5a75cd7134c87",
                                "operator": "==",
                                "value": "content_grid"
                            }
                        ]
                    ],
                    "wrapper": {
                        "width": "",
                        "class": "",
                        "id": ""
                    },
                    "placement": "top",
                    "endpoint": 0
                },
                {
                    "key": "field_5a7aeaca5b777",
                    "label": "Content Grid Selection",
                    "name": "content_grid_selection",
                    "type": "clone",
                    "instructions": "",
                    "required": 0,
                    "conditional_logic": 0,
                    "wrapper": {
                        "width": "",
                        "class": "",
                        "id": ""
                    },
                    "clone": [
                        "group_5a7ae65eb260a"
                    ],
                    "display": "seamless",
                    "layout": "block",
                    "prefix_label": 0,
                    "prefix_name": 0
                },
                {
                    "key": "field_5a75cdc934c88",
                    "label": "Custom HTML",
                    "name": "",
                    "type": "tab",
                    "instructions": "",
                    "required": 0,
                    "conditional_logic": [
                        [
                            {
                                "field": "field_5a75cd7134c87",
                                "operator": "==",
                                "value": "html"
                            }
                        ]
                    ],
                    "wrapper": {
                        "width": "",
                        "class": "",
                        "id": ""
                    },
                    "placement": "top",
                    "endpoint": 0
                },
                {
                    "key": "field_5a75cdd434c89",
                    "label": "Custom HTML Selection",
                    "name": "carousel_selection",
                    "type": "clone",
                    "instructions": "",
                    "required": 0,
                    "conditional_logic": 0,
                    "wrapper": {
                        "width": "",
                        "class": "",
                        "id": ""
                    },
                    "clone": [
                        "group_5a75cc6e1d27a"
                    ],
                    "display": "seamless",
                    "layout": "block",
                    "prefix_label": 0,
                    "prefix_name": 0
                }
            ]
        }
    ],
    "location": [
        [
            {
                "param": "options_page",
                "operator": "==",
                "value": "theme-leading-area"
            }
        ]
    ],
    "menu_order": 0,
    "position": "normal",
    "style": "default",
    "label_placement": "top",
    "instruction_placement": "field",
    "hide_on_screen": "",
    "active": 1,
    "description": "",
    "modified": 1518005033
}